theme/__init__.py
theme/apps.py
theme/filters.py
theme/forms.py
theme/settings.py
theme/urls.py
theme/utils.py
theme/views.py
theme/widgets.py
theme/static/admin/js/jquery.init.js
theme/static/admin/js/vendor/jquery/jquery.js
theme/static/admin/js/vendor/jquery/jquery.min.js
theme/static/admin/js/vendor/jquery/real_jquery.js
theme/static/admin/js/vendor/jquery/real_jquery.min.js
theme/static/assets/logo-big.png
theme/static/assets/logo.jpg
theme/static/assets/logo.png
theme/static/assets/css/atlantis.css
theme/static/assets/css/demo.css
theme/static/assets/css/error-codes.css
theme/static/assets/css/surface.css
theme/static/assets/img/slavatar.png
theme/static/assets/js/atlantis.js
theme/static/assets/js/atlantis.min.js
theme/static/assets/js/preload.js
theme/static/assets/js/surface.js
theme/static/assets/js/plugin/moment.min.js
theme/static/assets/js/plugin/select2.min.js
theme/static/assets/js/plugin/tempusdominus-bootstrap-4.min.js
theme/static/assets/js/plugin/chart-circle/circles.min.js
theme/static/assets/js/plugin/chart.js/chart.min.js
theme/static/assets/js/plugin/jquery-ui-touch-punch/jquery.ui.touch-punch.min.js
theme/static/assets/js/plugin/jqvmap/jquery.vmap.min.js
theme/static/assets/js/plugin/jqvmap/maps/jquery.vmap.algeria.js
theme/static/assets/js/plugin/jqvmap/maps/jquery.vmap.argentina.js
theme/static/assets/js/plugin/jqvmap/maps/jquery.vmap.brazil.js
theme/static/assets/js/plugin/jqvmap/maps/jquery.vmap.canada.js
theme/static/assets/js/plugin/jqvmap/maps/jquery.vmap.croatia.js
theme/static/assets/js/plugin/jqvmap/maps/jquery.vmap.europe.js
theme/static/assets/js/plugin/jqvmap/maps/jquery.vmap.france.js
theme/static/assets/js/plugin/jqvmap/maps/jquery.vmap.germany.js
theme/static/assets/js/plugin/jqvmap/maps/jquery.vmap.greece.js
theme/static/assets/js/plugin/jqvmap/maps/jquery.vmap.indonesia.js
theme/static/assets/js/plugin/jqvmap/maps/jquery.vmap.iran.js
theme/static/assets/js/plugin/jqvmap/maps/jquery.vmap.iraq.js
django_surface_theme-0.0.2.dist-info/LICENSE
django_surface_theme-0.0.2.dist-info/METADATA
django_surface_theme-0.0.2.dist-info/WHEEL
django_surface_theme-0.0.2.dist-info/top_level.txt
django_surface_theme-0.0.2.dist-info/RECORD
